vclog/__init__.py
vclog/logger.py
vclog-1.1.1.dist-info/LICENSE
vclog-1.1.1.dist-info/METADATA
vclog-1.1.1.dist-info/WHEEL
vclog-1.1.1.dist-info/top_level.txt
vclog-1.1.1.dist-info/RECORD
