Metadata-Version: 2.1
Name: vclog
Version: 1.1.1
Summary: Vistor's Console Logger (VCLog) offers a minimal and colorful console logging. Single-script. No dependencies.
Author: Vistor
Project-URL: Homepage, https://github.com/vistormu/vclog
Project-URL: Bug Tracker, https://github.com/vistormu/vclog/issues
Classifier: Programming Language :: Python :: 3
Classifier: License :: OSI Approved :: MIT License
Classifier: Operating System :: OS Independent
Requires-Python: >=3.10
License-File: LICENSE
